<!DOCTYPE DMHelperXML>
<root>
 <campaign name="Darkore Mine" minorVersion="0" time="0" worldSettingsExpanded="0" date="01/01/0000" worldNPCsExpanded="0" calendar="Gregorian" _baseID="{ab33cb67-2e6e-4b06-9771-20c3743dd9c9}" worldExpanded="1" partyExpanded="0" adventuresExpanded="1" majorVersion="1">
  <notes>
   <encounter name="" _baseID="{d7694b9a-cc2f-4c74-9c31-d61812229c74}" type="1"><![CDATA[]]></encounter>
  </notes>
  <characters/>
  <adventures>
   <adventure expanded="1" name="Darkore Mine" _baseID="{8438d0c8-0546-43ef-9bca-5e08c690079c}">
    <encounters/>
    <maps>
     <map name="Desert Waterfall Intro" audiotrack="{00000000-0000-0000-0000-000000000000}" filename="videos/Desert Waterfall.mp4" _baseID="{fc9eb221-68fa-425f-bc5b-bd909158488a}">
      <actions>
       <action a="0" r="0" b="0" g="0" type="0"/>
      </actions>
     </map>
     <map name="Desert Waterfall" audiotrack="{00000000-0000-0000-0000-000000000000}" filename="images/Desert Waterfall.jpg" _baseID="{23e1d5b2-6dee-4391-a54f-41f46726b9d8}">
      <actions>
       <action erase="1" radius="30" brushtype="0" type="1" smooth="0">
        <points>
         <point x="855" y="547"/>
         <point x="852" y="551"/>
        </points>
       </action>
      </actions>
     </map>
     <map name="Cavern Crossroads" audiotrack="{00000000-0000-0000-0000-000000000000}" filename="videos/Cavern Crossroad.mp4" _baseID="{e46e98f3-1b52-4d11-81ac-29be9cc2cf84}">
      <actions>
       <action a="0" r="0" b="0" g="0" type="0"/>
      </actions>
     </map>
     <map name="Cavern Crossroads - Still" audiotrack="{00000000-0000-0000-0000-000000000000}" filename="images/Cavern Crossroad.jpg" _baseID="{8a3b9c62-5821-4f17-a328-d48e1a870c41}">
      <actions>
       <action a="0" r="0" b="0" g="0" type="0"/>
      </actions>
     </map>
    </maps>
   </adventure>
  </adventures>
  <settings/>
  <npcs/>
  <tracks/>
 </campaign>
</root>
